capitolgains/__init__.py
capitolgains/core/__init__.py
capitolgains/core/congress.py
capitolgains/core/representative.py
capitolgains/core/senator.py
capitolgains/utils/__init__.py
capitolgains/utils/representative_scraper.py
capitolgains/utils/senator_scraper.py
capitolgains-0.1.0.dist-info/LICENSE
capitolgains-0.1.0.dist-info/METADATA
capitolgains-0.1.0.dist-info/WHEEL
capitolgains-0.1.0.dist-info/top_level.txt
capitolgains-0.1.0.dist-info/RECORD
