Metadata-Version: 2.2
Name: capitolgains
Version: 0.1.0
Summary: A Python package for retrieving and analyzing financial disclosure data from members of Congress
Author: Will Mundy
Project-URL: Homepage, https://github.com/thewillmundy/capitolgains
Project-URL: Bug Tracker, https://github.com/thewillmundy/capitolgains/issues
Classifier: Programming Language :: Python :: 3
Classifier: Programming Language :: Python :: 3.8
Classifier: Programming Language :: Python :: 3.9
Classifier: Programming Language :: Python :: 3.10
Classifier: Programming Language :: Python :: 3.11
Classifier: License :: OSI Approved :: MIT License
Classifier: Operating System :: OS Independent
Classifier: Development Status :: 4 - Beta
Classifier: Intended Audience :: Developers
Classifier: Intended Audience :: Financial and Insurance Industry
Classifier: Topic :: Office/Business :: Financial :: Investment
Classifier: Topic :: Software Development :: Libraries :: Python Modules
Requires-Python: >=3.8
License-File: LICENSE
Requires-Dist: requests>=2.31.0
Requires-Dist: python-dotenv>=1.0.0
Requires-Dist: playwright>=1.41.0
Requires-Dist: appdirs>=1.4.4
Provides-Extra: dev
Requires-Dist: pytest>=7.4.0; extra == "dev"
Requires-Dist: pytest-timeout>=2.1.0; extra == "dev"
Requires-Dist: pytest-playwright>=0.4.0; extra == "dev"
